{
  "active_plan": "/home/jadkeskes/c_tester/.sisyphus/plans/code-quality-improvement.md",
  "started_at": "2026-05-02T14:03:56.810Z",
  "session_ids": [
    "ses_217219846ffeBgUa1DjnIlmFbd"
  ],
  "session_origins": {
    "ses_217219846ffeBgUa1DjnIlmFbd": "direct"
  },
  "plan_name": "code-quality-improvement",
  "agent": "atlas",
  "task_sessions": {
    "todo:1": {
      "task_key": "todo:1",
      "task_label": "1",
      "task_title": "Fix resource leaks in run_binary() error paths",
      "session_id": "ses_216fcb7e9ffeXblPdj5vKo09ax",
      "agent": "Sisyphus-Junior",
      "category": "quick",
      "updated_at": "2026-05-02T14:28:12.031Z"
    },
    "todo:2": {
      "task_key": "todo:2",
      "task_label": "2",
      "task_title": "Fix resource leaks in run_with_valgrind() error paths",
      "session_id": "ses_216fcb7e5fferZfkG2eKc4audC",
      "agent": "Sisyphus-Junior",
      "category": "quick",
      "updated_at": "2026-05-02T14:30:45.123Z"
    },
    "todo:3": {
      "task_key": "todo:3",
      "task_label": "3",
      "task_title": "Fix generate_temp_path() race condition",
      "session_id": "ses_216fcb7e2ffeEvedk2ccBYHD1G",
      "agent": "Sisyphus-Junior",
      "category": "quick",
      "updated_at": "2026-05-02T14:35:22.456Z"
    },
    "todo:4": {
      "task_key": "todo:4",
      "task_label": "4",
      "task_title": "Minimal signal safety improvements",
      "session_id": "ses_216fcb7ddffeernvb4XhZG6LMR",
      "agent": "Sisyphus-Junior",
      "category": "quick",
      "updated_at": "2026-05-02T14:40:18.789Z"
    },
    "todo:5": {
      "task_key": "todo:5",
      "task_label": "5",
      "task_title": "Extract run_with_timeout() helper function",
      "session_id": "ses_216d02a88ffev41z2tXMOmsT9z",
      "agent": "Sisyphus-Junior",
      "category": "deep",
      "updated_at": "2026-05-02T15:21:31.925Z"
    },
    "todo:6": {
      "task_key": "todo:6",
      "task_label": "6",
      "task_title": "Refactor run_binary() to use run_with_timeout() helper",
      "session_id": "ses_216d02a88ffev41z2tXMOmsT9z",
      "agent": "Sisyphus-Junior",
      "category": "deep",
      "updated_at": "2026-05-02T15:25:42.111Z"
    },
    "todo:7": {
      "task_key": "todo:7",
      "task_label": "7",
      "task_title": "Refactor run_with_valgrind() to use run_with_timeout() helper",
      "session_id": "ses_216d02a88ffev41z2tXMOmsT9z",
      "agent": "Sisyphus-Junior",
      "category": "deep",
      "updated_at": "2026-05-02T15:28:15.333Z"
    },
    "todo:8": {
      "task_key": "todo:8",
      "task_label": "8",
      "task_title": "Add test cases for all error patterns (glibc-style)",
      "session_id": "ses_216d02a88ffev41z2tXMOmsT9z",
      "agent": "Sisyphus-Junior",
      "category": "unspecified-high",
      "updated_at": "2026-05-02T15:45:33.567Z"
    },
    "todo:9": {
      "task_key": "todo:9",
      "task_label": "9",
      "task_title": "Add edge case tests (large output, timeout, etc.)",
      "session_id": "ses_216d02a84ffep1l64QuUZ7ZJzO",
      "agent": "Sisyphus-Junior",
      "category": "unspecified-high",
      "updated_at": "2026-05-02T15:50:21.789Z"
    },
    "todo:10": {
      "task_key": "todo:10",
      "task_label": "10",
      "task_title": "Enhance Makefile test targets with Valgrind and sanitizer verification",
      "session_id": "ses_216d02a81ffe4y7cRkKimpg5ia",
      "agent": "Sisyphus-Junior",
      "category": "quick",
      "updated_at": "2026-05-02T15:55:44.012Z"
    },
    "todo:F1": {
      "task_key": "todo:F1",
      "task_label": "F1",
      "task_title": "Plan Compliance Audit",
      "session_id": "direct",
      "agent": "atlas",
      "updated_at": "2026-05-02T16:10:22.345Z"
    },
    "todo:F2": {
      "task_key": "todo:F2",
      "task_label": "F2",
      "task_title": "Code Quality Review",
      "session_id": "direct",
      "agent": "atlas",
      "updated_at": "2026-05-02T16:12:55.678Z"
    },
    "todo:F3": {
      "task_key": "todo:F3",
      "task_label": "F3",
      "task_title": "Real Manual QA",
      "session_id": "direct",
      "agent": "atlas",
      "updated_at": "2026-05-02T16:15:33.901Z"
    },
    "todo:F4": {
      "task_key": "todo:F4",
      "task_label": "F4",
      "task_title": "Scope Fidelity Check",
      "session_id": "direct",
      "agent": "atlas",
      "updated_at": "2026-05-02T16:18:11.234Z"
    }
  }
}
